quickLabel/__init__.py
quickLabel/handler.py
quickLabel/quickLabel.py
quickLabel-1.0.2.dist-info/DESCRIPTION.rst
quickLabel-1.0.2.dist-info/METADATA
quickLabel-1.0.2.dist-info/RECORD
quickLabel-1.0.2.dist-info/WHEEL
quickLabel-1.0.2.dist-info/metadata.json
quickLabel-1.0.2.dist-info/top_level.txt
