Metadata-Version: 2.0
Name: quickLabel
Version: 1.0.2
Summary: An image labeling tool for deep learning datasets.
Home-page: https://github.com/avlaskin
Author: Alexey Vlaskin
Author-email: alex@avlaskin.com
License: UNKNOWN
Platform: UNKNOWN
Requires-Dist: pillow
